digicircuit/__init__.py
digicircuit/boolean_parser.py
digicircuit/boolean_to_circuit.py
digicircuit/circuit.py
digicircuit/gate.py
digicircuit/kmap.py
digicircuit/latex_export.py
digitalcircuit-0.1.0.dist-info/licenses/LICENSE
digitalcircuit-0.1.0.dist-info/METADATA
digitalcircuit-0.1.0.dist-info/WHEEL
digitalcircuit-0.1.0.dist-info/entry_points.txt
digitalcircuit-0.1.0.dist-info/top_level.txt
digitalcircuit-0.1.0.dist-info/RECORD
